{
    "layout": "legacy.njk",
    "title": "Philpott Law Firm Legal Services DeLand, Daytona Beach, Sanford, Orange City, Deltona",
    "header": "Defending DeLand in Family Law, Criminal Law, & Civil Law",
    "metaDescription": "When You Need an Experienced Trial Attorney to Represent You in Divorce, Child Support, or Criminal Defense Proceedings, Call 386-873-2884 Today!",
    "metaKeywords": [
        "law firm",
        "family law",
        "divorce",
        "child support",
        "criminal defense",
        "lawyer",
        "attorney",
        "deland",
        "deltona",
        "orange city",
        "daytona beach",
        "sanford"
    ]
}